sharedql/__init__.py
sharedql/base.py
sharedql/schema.py
sharedql-0.3.dist-info/METADATA
sharedql-0.3.dist-info/RECORD
sharedql-0.3.dist-info/WHEEL
sharedql-0.3.dist-info/top_level.txt
